Metadata-Version: 1.1
Name: converse
Version: 0.1a3
Summary: Conversational Analytics and Plotting Library
Home-page: https://github.com/hrishioa/converse
Author: Hrishi Olickel
Author-email: hrishioa@gmail.com
License: GNU General Public License v3
Keywords: sentiment,messenger,chatbot,sentiment-analysis
Platform: UNKNOWN
Classifier: Programming Language :: Python :: 2
Classifier: Development Status :: 3 - Alpha
Classifier: Intended Audience :: Developers
Classifier: License :: OSI Approved :: GNU General Public License v3 (GPLv3)
Classifier: Operating System :: OS Independent
